{"FANTASTIC": {"1": {"Root": null, "Derive": null, "Meaning": "extraordinarily good or great; used especially as intensifiers", "Function": "Adjective", "Sentence": [], "Synonyms": ["Wonderful", "Howling", "Wondrous", "Rattling", "Fantastical"], "Antonyms": []}, "2": {"Root": null, "Derive": null, "Meaning": "fanciful and unrealistic; foolish", "Function": "Adjective", "Sentence": [], "Synonyms": ["Wonderful", "Howling", "Wondrous", "Rattling", "Fantastical"], "Antonyms": []}, "4": {"Root": null, "Derive": null, "Meaning": "extravagantly fanciful in design, construction, appearance", "Function": "Adjective", "Sentence": [], "Synonyms": ["Wonderful", "Howling", "Wondrous", "Rattling", "Fantastical"], "Antonyms": []}}}